AUTHORS
CHANGES.md
LICENSE
MANIFEST.in
Makefile
README.rst
__init__.py
setup.cfg
setup.py
alstat/__init__.py
alstat/console.py
alstat/utils.py
alstat.egg-info/PKG-INFO
alstat.egg-info/SOURCES.txt
alstat.egg-info/dependency_links.txt
alstat.egg-info/entry_points.txt
alstat.egg-info/top_level.txt
alstat/parsers/__init__.py
alstat/parsers/base.py
alstat/parsers/nginx.py
tests/__init__.py
tests/logs/access.nginx.1.log