Metadata-Version: 1.0
Name: alstat
Version: 0.0.7
Summary: Collection of advanced utils to parse logfiles in different formats and build statistic reports
Home-page: https://github.com/lispython/alstat
Author: Alexandr Lispython
Author-email: alex@obout.ru
License: BSD
Platform: Linux
Platform: Mac
Classifier: Environment :: Web Environment
Classifier: License :: OSI Approved :: BSD License
Classifier: Programming Language :: Python
Classifier: Operating System :: MacOS :: MacOS X
Classifier: Operating System :: POSIX
Classifier: Topic :: Internet
Classifier: Topic :: Software Development :: Libraries
